bdface/__init__.py
bdface/facebaidu.py
BaiduFace-1.4.dist-info/METADATA
BaiduFace-1.4.dist-info/WHEEL
BaiduFace-1.4.dist-info/top_level.txt
BaiduFace-1.4.dist-info/RECORD
