Metadata-Version: 2.1
Name: BaiduFace
Version: 1.4
Summary: 调用百度人脸识别推荐系统
Home-page: UNKNOWN
Author: wcy
Author-email: 1208640961@qq.com
License: UNKNOWN
Platform: UNKNOWN
